README.md
setup.cfg
setup.py
codigo_avulso_test/__init__.py
codigo_avulso_test/circulo.py
codigo_avulso_test/figura_geometrica.py
codigo_avulso_test/quadrado.py
codigo_avulso_test_tutorial_robson.egg-info/PKG-INFO
codigo_avulso_test_tutorial_robson.egg-info/SOURCES.txt
codigo_avulso_test_tutorial_robson.egg-info/dependency_links.txt
codigo_avulso_test_tutorial_robson.egg-info/top_level.txt
test/__init__.py
test/circulo_test.py
test/figura_geometrica_test.py
test/quadrado_test.py