Metadata-Version: 1.0
Name: codigo-avulso-test-tutorial-robson
Version: 0.1.1
Summary: Tutorial de teste unitário em Python para o blog Código Avulso
Home-page: https://github.com/mstuttgart/codigo-avulso-test-tutorial
Author: Michell Stuttgart
Author-email: michellstut@gmail.com
License: MIT License
Keywords: tutorial test unittest codigoavulso
Platform: UNKNOWN
